[
    {
        "bloque": "FRENTE PARA LA VICTORIA",
        "img": "http://www.legischubut2.gov.ar/images/2016/fpv/torres.JPG",
        "nombre": "Torres Otarola, María C."
    },
    {
        "bloque": "FRENTE PARA LA VICTORIA",
        "img": "http://www.legischubut2.gov.ar/images/2016/fpv/navarro.JPG",
        "nombre": "Navarro, Viviana E."
    },
    {
        "bloque": "FRENTE PARA LA VICTORIA",
        "img": "http://www.legischubut2.gov.ar/images/2016/fpv/tourinan.JPG",
        "nombre": "Touriñan, Javier Hugo"
    },
    {
        "bloque": "FRENTE PARA LA VICTORIA",
        "img": "http://www.legischubut2.gov.ar/images/2016/fpv/dufour.JPG",
        "nombre": "Dufour, Gabriela"
    },
    {
        "bloque": "FRENTE PARA LA VICTORIA",
        "img": "http://www.legischubut2.gov.ar/images/2016/fpv/mezaevans.JPG",
        "nombre": "Meza Evans, Hefin Blas"
    },
    {
        "bloque": "FRENTE PARA LA VICTORIA",
        "img": "http://www.legischubut2.gov.ar/images/2016/fpv/fita.JPG",
        "nombre": "Fita, Gustavo"
    },
    {
        "bloque": "FRENTE PARA LA VICTORIA",
        "img": "http://www.legischubut2.gov.ar/images/2016/fpv/gomez.JPG",
        "nombre": "Gomez, Carlos"
    },
    {
        "bloque": "FRENTE PARA LA VICTORIA",
        "img": "http://www.legischubut2.gov.ar/images/2016/fpv/gonzalez.JPG",
        "nombre": "Gonzalez, David"
    },
    {
        "bloque": "FRENTE PARA LA VICTORIA",
        "img": "http://www.legischubut2.gov.ar/images/2016/fpv/grazzini.JPG",
        "nombre": "Grazzini Agüero, José M"
    },
    {
        "bloque": "FRENTE PARA LA VICTORIA",
        "img": "http://www.legischubut2.gov.ar/images/2016/fpv/hernandez.JPG",
        "nombre": "Hernández, Estela B."
    },
    {
        "bloque": "FRENTE PARA LA VICTORIA",
        "img": "http://www.legischubut2.gov.ar/images/2016/fpv/marcilla.JPG",
        "nombre": "Marcilla, Beatriz A."
    },
    {
        "bloque": "FRENTE DE AGRUPACIONES",
        "img": "http://www.legischubut2.gov.ar/images/2016/fpv/papaiani.JPG",
        "nombre": "Papaiani, Maria Florencia"
    },
    {
        "bloque": "FRENTE DE AGRUPACIONES",
        "img": "http://www.legischubut2.gov.ar/images/2016/fpv/espinosa.JPG",
        "nombre": "Espinosa, Leandro"
    },
    {
        "bloque": "FRENTE DE AGRUPACIONES",
        "img": "http://www.legischubut2.gov.ar/images/2016/fpv/cunha.JPG",
        "nombre": "Cunha, Javier"
    },
    {
        "bloque": "CHUBUT SOMOS TODOS",
        "img": "http://www.legischubut2.gov.ar/images/2016/mcht/albaini.JPG",
        "nombre": "Albaini, Antonio A."
    },
    {
        "bloque": "CHUBUT SOMOS TODOS",
        "img": "http://www.legischubut2.gov.ar/images/2016/mcht/anden.JPG",
        "nombre": "Anden, Zulema M."
    },
    {
        "bloque": "CHUBUT SOMOS TODOS",
        "img": "http://www.legischubut2.gov.ar/images/2016/mcht/de_Luca.JPG",
        "nombre": "De Luca, María C."
    },
    {
        "bloque": "CHUBUT SOMOS TODOS",
        "img": "http://www.legischubut2.gov.ar/images/2016/mcht/garcia2.jpg",
        "nombre": "García, Jerónimo"
    },
    {
        "bloque": "CHUBUT SOMOS TODOS",
        "img": "http://www.legischubut2.gov.ar/images/2016/mcht/johnson.JPG",
        "nombre": "Johnson Táccari, A."
    },
    {
        "bloque": "CHUBUT SOMOS TODOS",
        "img": "http://www.legischubut2.gov.ar/images/2016/mcht/lopez.JPG",
        "nombre": "López, Adrián G."
    },
    {
        "bloque": "CHUBUT SOMOS TODOS",
        "img": "http://www.legischubut2.gov.ar/images/2016/mcht/ingram.JPG",
        "nombre": "Ingram, Roddy E."
    },
    {
        "bloque": "CHUBUT SOMOS TODOS",
        "img": "http://www.legischubut2.gov.ar/images/2016/mcht/mansilla.JPG",
        "nombre": "Mansilla, Mario E."
    },
    {
        "bloque": "CONVERGENCIA",
        "img": "http://www.legischubut2.gov.ar/images/2016/fpv/difilippo.JPG",
        "nombre": "Di Filippo,"
    },
    {
        "bloque": "CONVERGENCIA",
        "img": "http://www.legischubut2.gov.ar/images/2016/fpv/bruscoli.JPG",
        "nombre": "Bruscoli, Sergio Mario"
    },
    {
        "bloque": "U.C.R. - CAMBIEMOS",
        "img": "http://www.legischubut2.gov.ar/images/2016/cambiemos/caminoa.JPG",
        "nombre": ""
    },
    {
        "bloque": "U.C.R. - CAMBIEMOS",
        "img": "http://www.legischubut2.gov.ar/images/2016/cambiemos/conde.JPG",
        "nombre": "Conde, Eduardo José"
    },
    {
        "bloque": "U.C.R. - CAMBIEMOS",
        "img": "http://www.legischubut2.gov.ar/images/2016/cambiemos/pagliaroni.JPG",
        "nombre": "Pagliaroni, Manuel Iván"
    }
]